{
  "version": "1.0",
  "created_at": "2026-07-16T12:40:27.491Z",
  "total_topics": 15,
  "topics": [
    {
      "title": "Definition of Project Initiation Document (PID)",
      "slug": "definition-of-project-initiation-document-pid",
      "summary": "Explains what a Project Initiation Document (PID) is and its core components.",
      "category": "Project Management",
      "difficulty": "Basic",
      "keywords": [
        "Project Initiation Document",
        "PID",
        "definition",
        "project scope",
        "project management"
      ],
      "tags": [
        "definition",
        "project-management",
        "documentation"
      ],
      "topic_file": "topics/definition-of-project-initiation-document-pid.md",
      "metadata_file": "metadata/definition-of-project-initiation-document-pid.json"
    },
    {
      "title": "Importance of a Project Initiation Document",
      "slug": "importance-of-pid",
      "summary": "Describes why a PID is critical for project success and the risks of omitting it.",
      "category": "Project Management",
      "difficulty": "Basic",
      "keywords": [
        "project success",
        "project start",
        "risk mitigation",
        "PID importance"
      ],
      "tags": [
        "best-practices",
        "risk-management"
      ],
      "topic_file": "topics/importance-of-pid.md",
      "metadata_file": "metadata/importance-of-pid.json"
    },
    {
      "title": "Alternative Names for Project Initiation Document",
      "slug": "alternative-names-for-pid",
      "summary": "Lists other common terms used for a PID across methodologies.",
      "category": "Project Management",
      "difficulty": "Basic",
      "keywords": [
        "project charter",
        "project brief",
        "PID synonyms"
      ],
      "tags": [
        "terminology",
        "project-management"
      ],
      "topic_file": "topics/alternative-names-for-pid.md",
      "metadata_file": "metadata/alternative-names-for-pid.json"
    },
    {
      "title": "Seven Steps to Create a Project Initiation Document",
      "slug": "steps-to-create-pid",
      "summary": "Provides an overview of the seven core sections needed in a PID.",
      "category": "Project Management",
      "difficulty": "Intermediate",
      "keywords": [
        "PID steps",
        "project initiation process",
        "project planning"
      ],
      "tags": [
        "process",
        "workflow",
        "project-management"
      ],
      "topic_file": "topics/steps-to-create-pid.md",
      "metadata_file": "metadata/steps-to-create-pid.json"
    },
    {
      "title": "Provide the Context",
      "slug": "provide-context",
      "summary": "Describes the information needed to set project context in the PID.",
      "category": "Project Management",
      "difficulty": "Basic",
      "keywords": [
        "project context",
        "business drivers",
        "mission statement"
      ],
      "tags": [
        "context",
        "project-start"
      ],
      "topic_file": "topics/provide-context.md",
      "metadata_file": "metadata/provide-context.json"
    },
    {
      "title": "Define the Project Parameters",
      "slug": "define-project-parameters",
      "summary": "Outlines how to document budget, timeline, collaboration, and primary targets.",
      "category": "Project Management",
      "difficulty": "Intermediate",
      "keywords": [
        "budget",
        "timeline",
        "project constraints",
        "collaboration model"
      ],
      "tags": [
        "planning",
        "budgeting",
        "scheduling"
      ],
      "topic_file": "topics/define-project-parameters.md",
      "metadata_file": "metadata/define-project-parameters.json"
    },
    {
      "title": "Define the Specifics",
      "slug": "define-specifics",
      "summary": "Details how to capture scope, requirements, boundaries, and deliverables.",
      "category": "Project Management",
      "difficulty": "Intermediate",
      "keywords": [
        "scope",
        "in‑scope",
        "out‑of‑scope",
        "deliverables",
        "assumptions"
      ],
      "tags": [
        "scope-management",
        "requirements"
      ],
      "topic_file": "topics/define-specifics.md",
      "metadata_file": "metadata/define-specifics.json"
    },
    {
      "title": "Project Breakdown Structure and Resourcing Plan",
      "slug": "project-breakdown-and-resourcing",
      "summary": "Explains how to create a Work Breakdown Structure (WBS) and allocate resources.",
      "category": "Project Management",
      "difficulty": "Intermediate",
      "keywords": [
        "WBS",
        "work breakdown structure",
        "resource allocation",
        "project planning"
      ],
      "tags": [
        "planning",
        "resource-management"
      ],
      "topic_file": "topics/project-breakdown-and-resourcing.md",
      "metadata_file": "metadata/project-breakdown-and-resourcing.json"
    },
    {
      "title": "Define Who’s Who (Team Structure & RACI)",
      "slug": "define-whos-who",
      "summary": "Shows how to document internal and external team roles and create a RACI matrix.",
      "category": "Project Management",
      "difficulty": "Intermediate",
      "keywords": [
        "team roles",
        "RACI",
        "responsibility matrix",
        "stakeholder map"
      ],
      "tags": [
        "governance",
        "communication"
      ],
      "topic_file": "topics/define-whos-who.md",
      "metadata_file": "metadata/define-whos-who.json"
    },
    {
      "title": "RACI Chart Explanation",
      "slug": "racichart-explanation",
      "summary": "Defines the four RACI roles and their purpose in project governance.",
      "category": "Project Management",
      "difficulty": "Basic",
      "keywords": [
        "RACI",
        "responsibility matrix",
        "project governance"
      ],
      "tags": [
        "responsibility",
        "communication"
      ],
      "topic_file": "topics/racichart-explanation.md",
      "metadata_file": "metadata/racichart-explanation.json"
    },
    {
      "title": "Identify Risks, Assumptions, Issues, and Dependencies",
      "slug": "identify-risks-assumptions-issues-dependencies",
      "summary": "Guides how to capture potential project risks and mitigation strategies in the PID.",
      "category": "Project Management",
      "difficulty": "Intermediate",
      "keywords": [
        "risk register",
        "assumptions",
        "issues",
        "dependencies",
        "mitigation"
      ],
      "tags": [
        "risk-management",
        "planning"
      ],
      "topic_file": "topics/identify-risks-assumptions-issues-dependencies.md",
      "metadata_file": "metadata/identify-risks-assumptions-issues-dependencies.json"
    },
    {
      "title": "Share the Project Initiation Document",
      "slug": "share-pid",
      "summary": "Outlines best practices for distributing, signing off, and maintaining the PID.",
      "category": "Project Management",
      "difficulty": "Basic",
      "keywords": [
        "document distribution",
        "sign‑off",
        "version control",
        "stakeholder communication"
      ],
      "tags": [
        "communication",
        "governance"
      ],
      "topic_file": "topics/share-pid.md",
      "metadata_file": "metadata/share-pid.json"
    },
    {
      "title": "Using the PID as a Living Document",
      "slug": "pid-as-living-document",
      "summary": "Explains how to keep the PID up‑to‑date throughout the project lifecycle.",
      "category": "Project Management",
      "difficulty": "Intermediate",
      "keywords": [
        "living document",
        "document updates",
        "change management"
      ],
      "tags": [
        "maintenance",
        "change-management"
      ],
      "topic_file": "topics/pid-as-living-document.md",
      "metadata_file": "metadata/pid-as-living-document.json"
    },
    {
      "title": "When a PID May Not Be Required",
      "slug": "when-pid-not-required",
      "summary": "Identifies scenarios where creating a full PID might be unnecessary.",
      "category": "Project Management",
      "difficulty": "Basic",
      "keywords": [
        "project size",
        "lightweight brief",
        "when to skip PID"
      ],
      "tags": [
        "guidelines",
        "scope"
      ],
      "topic_file": "topics/when-pid-not-required.md",
      "metadata_file": "metadata/when-pid-not-required.json"
    },
    {
      "title": "Accessing a Project Initiation Document Template",
      "slug": "pid-template-access",
      "summary": "Provides information on where to obtain a ready‑made PID template.",
      "category": "Resources",
      "difficulty": "Basic",
      "keywords": [
        "PID template",
        "download",
        "membership"
      ],
      "tags": [
        "resources",
        "templates"
      ],
      "topic_file": "topics/pid-template-access.md",
      "metadata_file": "metadata/pid-template-access.json"
    }
  ]
}